{
  "project_info": {
    "project_number": "47801405336",
    "firebase_url": "https://ya-ganaste-e4427.firebaseio.com",
    "project_id": "ya-ganaste-e4427",
    "storage_bucket": "ya-ganaste-e4427.appspot.com"
  },
  "client": [
    {
      "client_info": {
        "mobilesdk_app_id": "1:47801405336:android:4ebc6fd4b0e54b51",
        "android_client_info": {
          "package_name": "com.pagatodo.yaganaste"
        }
      },
      "oauth_client": [
        {
          "client_id": "47801405336-1h0e6bp45vgsltl2vj16j5i6ae4t7nr5.apps.googleusercontent.com",
          "client_type": 3
        }
      ],
      "api_key": [
        {
          "current_key": "AIzaSyBJY6xouGAtwh5F9brJlXn1u8juF7P4VBs"
        }
      ],
      "services": {
        "analytics_service": {
          "status": 1
        },
        "appinvite_service": {
          "status": 1,
          "other_platform_oauth_client": []
        },
        "ads_service": {
          "status": 2
        }
      }
    }
  ],
  "configuration_version": "1"
}